common/__init__.py
common/decos.py
common/descryptors.py
common/errors.py
common/metaclasses.py
common/utils.py
common/variables.py
logs/__init__.py
logs/config_server_log.py
server_wd/__init__.py
server_wd/add_user.py
server_wd/config_window.py
server_wd/core.py
server_wd/database.py
server_wd/main_window.py
server_wd/remove_user.py
server_wd/stat_window.py
mess_srv156-0.1.0.dist-info/METADATA
mess_srv156-0.1.0.dist-info/WHEEL
mess_srv156-0.1.0.dist-info/top_level.txt
mess_srv156-0.1.0.dist-info/RECORD
